txtulip-0.1.0-py3.5-nspkg.pth
twisted/plugins/txtulip_reactor.py
txtulip/__init__.py
txtulip/eventloop.py
txtulip/reactor.py
txtulip-0.1.0.dist-info/DESCRIPTION.rst
txtulip-0.1.0.dist-info/METADATA
txtulip-0.1.0.dist-info/RECORD
txtulip-0.1.0.dist-info/WHEEL
txtulip-0.1.0.dist-info/metadata.json
txtulip-0.1.0.dist-info/namespace_packages.txt
txtulip-0.1.0.dist-info/top_level.txt
