Metadata-Version: 2.0
Name: txtulip
Version: 0.1.0
Summary: UNKNOWN
Home-page: https://github.com/graingert/txtulip
Author: Thomas Grainger
Author-email: txtulip@graingert.co.uk
License: MIT
Platform: UNKNOWN
Requires-Dist: twisted
